{
  "latest_local_contest_id": 4183,
  "last_published_commit": "2d5430a14564fe413e5ba2db3a55484b7737ff81",
  "per_algo_last_trained_contest_id": {
    "astra-moon": 4183,
    "classic-analisi-anomalie-pattern": 4183,
    "classic-co-occorrenze": 4183,
    "classic-coppie-terni-consecutivi": 4183,
    "classic-coppie-terzine-frequenti": 4183,
    "classic-distribuzioni-modelli-raggruppamento": 4183,
    "classic-frequency": 4183,
    "classic-ritardi": 4183,
    "classic-ritardi-combinazioni": 4183,
    "classic-statistiche-combinate-finestre-mobili": 4183,
    "classic-tavole-probabilita-teorica-test-uniformita": 4183,
    "genetic": 4183,
    "hispa": 4183,
    "paradox-logiche-decisionali-metriche": 4183,
    "super6NN": 4183
  },
  "last_card_hits_build_at": "2026-04-21T22:38:31",
  "last_card_hits_changed_cards": 9,
  "last_successful_run_id": "20260421_215910",
  "last_email_status": "Email inviata",
  "pending_publish": {},
  "consecutive_failures": 0,
  "last_failure_at": "",
  "last_failure_reason": "",
  "run_journal": [
    {
      "ts": "2026-04-21T21:59:10",
      "event": "lock_acquired",
      "run_id": "20260421_215910",
      "payload": {
        "lease_until": "2026-04-21T22:01:10"
      }
    },
    {
      "ts": "2026-04-21T22:47:13",
      "event": "lock_released",
      "run_id": "20260421_215910",
      "payload": {}
    }
  ],
  "last_quorum_policy": {
    "min_sources": 2,
    "gold_weight": 2,
    "max_skew_minutes": 180,
    "max_block_minutes": 15,
    "fallback_latest_source": true
  },
  "quorum_degraded_since": ""
}
